Metadata-Version: 2.1
Name: qtcd
Version: 0.0.0
Summary: P2P anonymous cryptocurrency protocol
Home-page: https://github.com/gamesguru/bitq
Author: gamesguru
Author-email: mathmuncher11@gmail.com
License: GPL v3
Platform: UNKNOWN
Classifier: Intended Audience :: End Users/Desktop
Classifier: Development Status :: 3 - Alpha
Classifier: License :: OSI Approved :: Apache Software License
Classifier: Operating System :: OS Independent
Classifier: Programming Language :: Python :: 3.6
Classifier: Programming Language :: Python :: 3.7
Classifier: Programming Language :: Python :: 3.8
Requires-Python: >=3.6.5
